telegrab/__init__.py
telegrab/__main__.py
telegrab/types.py
telegrab-0.0.6.dist-info/entry_points.txt
telegrab-0.0.6.dist-info/WHEEL
telegrab-0.0.6.dist-info/METADATA
telegrab-0.0.6.dist-info/RECORD
